[{"id":"6b7ff540-22d1-4ada-9875-3ef8708c5b83","name":"asdasda","surname":"asdsad","email":"asdsd@asdas.hh","age":"22","life-style":"abstemious","skin-type":"dry","location":"city"},{"id":"53505dde-756e-45a9-b8d8-8da9a99866d3","name":"asdasda","surname":"asdsad","email":"asdsd@asdas.hh","age":"22","life-style":"abstemious","skin-type":"dry","location":"city"},{"id":"0f62f4dd-90e7-4042-a2e2-acf2d24dff15","name":"Aasdsadadad","surname":"Aasdsadadad","email":"edanriell@gmail.com","age":"22","life-style":"active","skin-type":"dry","location":"suburb"},{"id":"7dfb0bae-44f9-40a6-a31c-e9f844b79e1e","name":"asdadasdsadas","surname":"asdsaddadd","email":"edanriell@gmail.com","age":"22","life-style":"abstemious","skin-type":"dry","location":"suburb"},{"id":"816f7208-5b0e-4f10-865c-a436732242c3","name":"asdasddadasdsadadads","surname":"asdsadadaasdd","email":"edanriell@gmail.com","age":"22","life-style":"active","skin-type":"dry","location":"city"}]